NetManage/__init__.py
NetManage/__main__.py
NetManage/utils/NMCOMM_file.py
NetManage/utils/NMCONN_file.py
NetManage/utils/__init__.py
NetManage/utils/commands.py
NetManage/utils/connections.py
NetManage-0.1.6.dist-info/METADATA
NetManage-0.1.6.dist-info/WHEEL
NetManage-0.1.6.dist-info/entry_points.txt
NetManage-0.1.6.dist-info/top_level.txt
NetManage-0.1.6.dist-info/RECORD
