Metadata-Version: 2.1
Name: NetManage
Version: 0.1.6
Author: Jakub Olejnik
Author-email: jacobole2000@gmail.com
Classifier: Programming Language :: Python :: 3
Classifier: License :: OSI Approved :: MIT License
Classifier: Operating System :: OS Independent
Requires-Python: >=3.6
